tivendor.py
tivendor-0.0.11.dist-info/METADATA
tivendor-0.0.11.dist-info/WHEEL
tivendor-0.0.11.dist-info/top_level.txt
tivendor-0.0.11.dist-info/RECORD
