Metadata-Version: 2.1
Name: tivendor
Version: 0.0.11
Summary: vendor request of taiqiyun [private]
Home-page: UNKNOWN
License: UNKNOWN
Platform: UNKNOWN
Requires-Dist: requests (>=2.22.0)
Requires-Dist: kafka-python (>=1.4.6)
Requires-Dist: redis (>=3.3.11)
